matchref/__init__.py
match_ref-1.0.1.dist-info/METADATA
match_ref-1.0.1.dist-info/WHEEL
match_ref-1.0.1.dist-info/top_level.txt
match_ref-1.0.1.dist-info/RECORD
