Metadata-Version: 2.1
Name: match-ref
Version: 1.0.1
Summary: Use top-level variable references in match cases
Home-page: https://github.com/squirrel-preslash/match-ref
Author: Squirrel-Preslash
License: MIT
Platform: UNKNOWN
Classifier: License :: OSI Approved :: MIT License
Classifier: Programming Language :: Python :: 3
Classifier: Programming Language :: Python :: 3.10
